pychess_engine/__init__.py
pychess_engine/attack.py
pychess_engine/bitboards.py
pychess_engine/board.py
pychess_engine/constants.py
pychess_engine/debug.py
pychess_engine/engine.py
pychess_engine/fens.py
pychess_engine/globals.py
pychess_engine/hashkeys.py
pychess_engine/helper.py
pychess_engine/init.py
pychess_engine/misc.py
pychess_engine/move.py
pychess_engine/perft.py
pychess_engine/pvtable.py
pychess_engine/search.py
pychess_engine/uci.py
pychess_engine/undo.py
pychess_engine/validate.py
pychess_engine-1.1.0.dist-info/licenses/LICENSE
pychess_engine-1.1.0.dist-info/METADATA
pychess_engine-1.1.0.dist-info/WHEEL
pychess_engine-1.1.0.dist-info/entry_points.txt
pychess_engine-1.1.0.dist-info/top_level.txt
pychess_engine-1.1.0.dist-info/RECORD
