Metadata-Version: 2.4
Name: pychess_engine
Version: 1.1.0
Summary: A lightweight chess engine written in Python. It can evaluate chess positions, calculate best moves, and integrate with various interfaces. It is designed to be simple and extensible, offering the flexibility to implement your own chess logic or use it as part of a larger project
Home-page: https://github.com/vanshugalhotra/pychess-engine
Author: Vanshu Galhotra
Author-email: galhotravanshu@gmail.com
Classifier: Programming Language :: Python :: 3
Classifier: License :: OSI Approved :: MIT License
Classifier: Operating System :: OS Independent
Classifier: Topic :: Games/Entertainment :: Board Games
Classifier: Intended Audience :: Developers
Requires-Python: >=3.7
License-File: LICENSE
Dynamic: author
Dynamic: author-email
Dynamic: classifier
Dynamic: description
Dynamic: description-content-type
Dynamic: home-page
Dynamic: license-file
Dynamic: requires-python
Dynamic: summary
